LICENSE
README.rst
setup.py
llmabba/__init__.py
llmabba/abba.py
llmabba/agg.pyx
llmabba/comp.pyx
llmabba/fkmns.py
llmabba/inverse.pyx
llmabba/llmabba.py
llmabba/models.py
llmabba/process.py
llmabba/quant.py
llmabba.egg-info/PKG-INFO
llmabba.egg-info/SOURCES.txt
llmabba.egg-info/dependency_links.txt
llmabba.egg-info/requires.txt
llmabba.egg-info/top_level.txt
llmabba/utils/__init__.py
llmabba/utils/data_loader.py
llmabba/utils/data_processor.py
llmabba/utils/fundamentals.py
llmabba/utils/regressor_tools.py
llmabba/utils/tools.py
llmabba/utils/transformer_tools.py