Metadata-Version: 2.2
Name: llmabba
Version: 0.0.2
Summary: LLM-ABBA: mining time series via symbolic approximation and large language models
Home-page: https://github.com/inEXASCALE/llmabba
Author: NA
Author-email: xinyechenai@email.com
License: BSD 3-Clause
Classifier: Intended Audience :: Science/Research
Classifier: Intended Audience :: Developers
Classifier: Programming Language :: Python
Classifier: Topic :: Software Development
Classifier: Topic :: Scientific/Engineering
Classifier: Operating System :: Microsoft :: Windows
Classifier: Operating System :: Unix
Classifier: Programming Language :: Python :: 3
License-File: LICENSE
Requires-Dist: numpy>=1.3.0
Requires-Dist: scipy>=0.7.0
Requires-Dist: requests
Requires-Dist: pandas
Requires-Dist: scikit-learn
Requires-Dist: pychop
Requires-Dist: cython>=0.27
Requires-Dist: joblib>=1.1.1
Requires-Dist: transformers
Requires-Dist: peft
Requires-Dist: trl
Requires-Dist: datasets
Requires-Dist: accelerate
Requires-Dist: matplotlib
Dynamic: author
Dynamic: author-email
Dynamic: classifier
Dynamic: description
Dynamic: description-content-type
Dynamic: home-page
Dynamic: license
Dynamic: requires-dist
Dynamic: summary
